python_project/__init__.py
python_project/__main__.py
python_project/cli/commands/.gitkeep
python_project/cli/root_command.py
python_project/cli/styles.py
python_project/tui/components/.gitkeep
python_project/tui/css/.gitkeep
python_project/tui/css/demo.tcss
python_project/tui/css/noctis.tcss
python_project/tui/main_window.py
python_project/tui/themes.py
python_project_galactipy-0.16.0.dist-info/METADATA
python_project_galactipy-0.16.0.dist-info/WHEEL
python_project_galactipy-0.16.0.dist-info/entry_points.txt
python_project_galactipy-0.16.0.dist-info/licenses/AUTHORS.md
python_project_galactipy-0.16.0.dist-info/licenses/LICENCE
python_project_galactipy-0.16.0.dist-info/RECORD
