Metadata-Version: 2.4
Name: python-project-galactipy
Version: 0.16.0
Summary: Awesome `python-project` is a Python cli/package created with https://gitlab.com/galactipy/galactipy
License: MIT
License-File: AUTHORS.md
License-File: LICENCE
Author: The Galactipy Contributors
Author-email: contact@galactipy.com
Maintainer: The Galactipy Contributors
Maintainer-email: contact@galactipy.com
Requires-Python: >=3.9
Classifier: Development Status :: 1 - Planning
Classifier: Environment :: Console
Classifier: Intended Audience :: Developers
Classifier: License :: OSI Approved :: MIT License
Classifier: Operating System :: OS Independent
Classifier: Programming Language :: Python :: 3
Classifier: Programming Language :: Python :: 3.9
Classifier: Programming Language :: Python :: 3.10
Classifier: Programming Language :: Python :: 3.11
Classifier: Programming Language :: Python :: 3.12
Classifier: Programming Language :: Python :: 3.13
Classifier: Programming Language :: Python :: 3.14
Classifier: Topic :: Software Development :: Libraries :: Python Modules
Classifier: Topic :: Terminals
Requires-Dist: art (>=6.5,<7.0)
Requires-Dist: rich (>=14.1.0,<15.0.0)
Requires-Dist: textual (>=6.1.0,<7.0.0)
Requires-Dist: typer[all] (>=0.18.0,<0.19.0)
Project-URL: Contributing Guidelines, https://gitlab.com/galactipy/python-project/-/tree/master/CONTRIBUTING.md
Project-URL: Homepage, https://gitlab.com/galactipy/python-project
Project-URL: Repository, https://gitlab.com/galactipy/python-project
Project-URL: Work Item Tracker, https://gitlab.com/galactipy/python-project/-/issues
